dulanceluks/DNU.txt
dulanceluks/__init__.py
dulanceluks/utils.py
dulanceluks-0.1.dist-info/METADATA
dulanceluks-0.1.dist-info/WHEEL
dulanceluks-0.1.dist-info/top_level.txt
dulanceluks-0.1.dist-info/RECORD
